[
  {
    "title": "Portfolio Overview",
    "description": "View a summary of your holdings, along with overall portfolio performance charts and data",
    "img": "lp_screens/screenshot_report-growth_1205x945-min.png",
    "img_alt": ""
  },
  {
    "title": "Performance",
    "description": "View detailed performance information for your chosen portfolio.",
    "img": "lp_screens/screenshot_report-performance_1205x945-min.png",
    "img_alt": ""
  },
  {
    "title": "Diversity",
    "description": "View your portfolio diversification across industry sectors, investment types, countries & markets.",
    "img": "lp_screens/screenshot_report-diversity-report_1205x945-min.png",
    "img_alt": ""
  },
  {
    "title": "Taxable Income",
    "description": "View a list of all dividend payments and interest payments received.",
    "img": "lp_screens/screenshot_report-taxable-income-ca_1205x945-min1.png",
    "img_alt": ""
  },
  {
    "title": "Capital Gains Tax (CGT)",
    "description": "View a list of capital gains earned, according to the selected sale allocation method.",
    "img": "lp_screens/screenshot_report-cgt-ca_1205x945-min.png",
    "img_alt": ""
  },
  {
    "title": "Historical Cost",
    "description": "View opening and closing balances at cost price along with the closing market value.",
    "img": "lp_screens/screenshot_report-historical-cost_1205x945-min.png",
    "img_alt": ""
  }
]
